dad_sql_pandas/__init__.py
dad_sql_pandas/dad_sql.py
dad_sql_pandas-0.1.1.dist-info/WHEEL
dad_sql_pandas-0.1.1.dist-info/METADATA
dad_sql_pandas-0.1.1.dist-info/RECORD
