Metadata-Version: 2.1
Name: dad-sql-pandas
Version: 0.1.1
Summary: Pandas implementation of the SQL Data Action Definition for FRIDAAY
Author: Ernest Prabhakar
Author-email: ernest.prabhakar@gmail.com
Requires-Python: >=3.9,<4.0
Classifier: Programming Language :: Python :: 3
Classifier: Programming Language :: Python :: 3.10
Classifier: Programming Language :: Python :: 3.9
Requires-Dist: pandas (>=1.4.3,<2.0.0)
